[
  {
    "timestamp": "2025-12-27T12:08:33.162668",
    "status": "pending",
    "nom": "romeo",
    "prenom": "heloise",
    "email": "heloise.romeo@gmail.com",
    "telephone": null,
    "objet": "JPO",
    "message": "bonjour, j'aimerais m'inscrire à une jpo comment faire",
    "service": "general",
    "service_email": "contact@esilv.fr"
  },
  {
    "timestamp": "2025-12-28T15:34:25.656430",
    "status": "pending",
    "nom": "romeo",
    "prenom": "heloise",
    "email": "heloise.romeo@gmail.com",
    "telephone": null,
    "objet": "JPO",
    "message": "bonjour je souhaiterais participer a une jpo",
    "service": "general",
    "service_email": "contact@esilv.fr"
  },
  {
    "timestamp": "2025-12-28T15:42:27.530130",
    "status": "pending",
    "nom": "romeo",
    "prenom": "heloise",
    "email": "heloise.romeo@gmail.com",
    "telephone": null,
    "objet": "jpo",
    "message": "bonjour j'aimerais participer a une jpo",
    "service": "general",
    "service_email": "contact@esilv.fr"
  }
]